[
  {
    "securityId": 9297,
    "totalTrades": 3686,
    "lastTradedPrice": 780.0,
    "securityName": "Bandipur Cablecar and Tourism Limited",
    "symbol": "BANDIPUR"
  },
  {
    "securityId": 9293,
    "totalTrades": 2196,
    "lastTradedPrice": 605.0,
    "securityName": "Daramkhola Hydro Energy Limited",
    "symbol": "DHEL"
  },
  {
    "securityId": 9296,
    "totalTrades": 2040,
    "lastTradedPrice": 618.2,
    "securityName": "Bungal Hydro Limited",
    "symbol": "BUNGAL"
  },
  {
    "securityId": 2913,
    "totalTrades": 1656,
    "lastTradedPrice": 669.0,
    "securityName": "Mountain Energy Nepal Limited",
    "symbol": "MEN"
  },
  {
    "securityId": 9287,
    "totalTrades": 1566,
    "lastTradedPrice": 737.0,
    "securityName": "Mabilung Energy Limited",
    "symbol": "MABEL"
  },
  {
    "securityId": 9267,
    "totalTrades": 1440,
    "lastTradedPrice": 511.0,
    "securityName": "Bikash Hydropower Company Limited",
    "symbol": "BHCL"
  },
  {
    "securityId": 2841,
    "totalTrades": 1264,
    "lastTradedPrice": 290.0,
    "securityName": "RASUWAGADHI HYDROPOWER COMPANY LIMITED",
    "symbol": "RHPL"
  },
  {
    "securityId": 134,
    "totalTrades": 1227,
    "lastTradedPrice": 193.9,
    "securityName": "Himalayan Bank Limited",
    "symbol": "HBL"
  },
  {
    "securityId": 2743,
    "totalTrades": 1017,
    "lastTradedPrice": 398.3,
    "securityName": "Ngadi Group Power Ltd.",
    "symbol": "NGPL"
  },
  {
    "securityId": 2831,
    "totalTrades": 975,
    "lastTradedPrice": 496.8,
    "securityName": "Union Hydropower Limited",
    "symbol": "UNHPL"
  },
  {
    "securityId": 8133,
    "totalTrades": 935,
    "lastTradedPrice": 292.0,
    "securityName": "Peoples Hydropower Company Limited",
    "symbol": "PHCL"
  },
  {
    "securityId": 9234,
    "totalTrades": 873,
    "lastTradedPrice": 851.0,
    "securityName": "Himalayan Reinsurance Limited",
    "symbol": "HRL"
  },
  {
    "securityId": 9270,
    "totalTrades": 781,
    "lastTradedPrice": 960.0,
    "securityName": "Him Star Urja Company Limited",
    "symbol": "HIMSTAR"
  },
  {
    "securityId": 8045,
    "totalTrades": 759,
    "lastTradedPrice": 540.0,
    "securityName": "Green Ventures Limited",
    "symbol": "GVL"
  },
  {
    "securityId": 686,
    "totalTrades": 678,
    "lastTradedPrice": 337.0,
    "securityName": "Barun Hydropower Co. Ltd.",
    "symbol": "BARUN"
  },
  {
    "securityId": 2760,
    "totalTrades": 657,
    "lastTradedPrice": 587.0,
    "securityName": "United Modi Hydropower Ltd.",
    "symbol": "UMHL"
  },
  {
    "securityId": 2789,
    "totalTrades": 637,
    "lastTradedPrice": 325.0,
    "securityName": "Joshi Hydropower Development Company Ltd",
    "symbol": "JOSHI"
  },
  {
    "securityId": 9263,
    "totalTrades": 607,
    "lastTradedPrice": 668.5,
    "securityName": "Sanvi Energy Limited",
    "symbol": "SANVI"
  },
  {
    "securityId": 9262,
    "totalTrades": 532,
    "lastTradedPrice": 789.0,
    "securityName": "Trade Tower Limited",
    "symbol": "TTL"
  },
  {
    "securityId": 2919,
    "totalTrades": 484,
    "lastTradedPrice": 275.0,
    "securityName": "Nepal Infrastructure Bank Limited",
    "symbol": "NIFRA"
  },
  {
    "securityId": 9199,
    "totalTrades": 483,
    "lastTradedPrice": 494.5,
    "securityName": "Reliable Nepal Life Insurance Limited",
    "symbol": "RNLI"
  },
  {
    "securityId": 2809,
    "totalTrades": 478,
    "lastTradedPrice": 587.4,
    "securityName": "SHIVAM CEMENTS LTD",
    "symbol": "SHIVM"
  },
  {
    "securityId": 8021,
    "totalTrades": 424,
    "lastTradedPrice": 555.0,
    "securityName": "Sahas Urja Limited",
    "symbol": "SAHAS"
  },
  {
    "securityId": 2744,
    "totalTrades": 422,
    "lastTradedPrice": 1218.0,
    "securityName": "Green Development Bank Ltd.",
    "symbol": "GRDBL"
  },
  {
    "securityId": 2881,
    "totalTrades": 416,
    "lastTradedPrice": 1331.0,
    "securityName": "Nepal Reinsurance Company Limited",
    "symbol": "NRIC"
  },
  {
    "securityId": 235,
    "totalTrades": 415,
    "lastTradedPrice": 1175.5,
    "securityName": "Himalayan Distillery Limited",
    "symbol": "HDL"
  },
  {
    "securityId": 255,
    "totalTrades": 404,
    "lastTradedPrice": 189.0,
    "securityName": "Prabhu  Bank Limited",
    "symbol": "PRVU"
  },
  {
    "securityId": 9201,
    "totalTrades": 399,
    "lastTradedPrice": 505.3,
    "securityName": "Sun Nepal Life Insurance Company Limited",
    "symbol": "SNLI"
  },
  {
    "securityId": 9258,
    "totalTrades": 399,
    "lastTradedPrice": 902.0,
    "securityName": "Pure Energy Limited",
    "symbol": "PURE"
  },
  {
    "securityId": 8031,
    "totalTrades": 385,
    "lastTradedPrice": 292.8,
    "securityName": "Madhya Bhotekoshi Jalavidyut Company Limited",
    "symbol": "MBJC"
  },
  {
    "securityId": 591,
    "totalTrades": 383,
    "lastTradedPrice": 541.9,
    "securityName": "Sanima Mai Hydropower Ltd.",
    "symbol": "SHPC"
  },
  {
    "securityId": 2807,
    "totalTrades": 343,
    "lastTradedPrice": 1179.0,
    "securityName": "Asha Laghubitta Bittiya Sanstha Ltd",
    "symbol": "ALBSL"
  },
  {
    "securityId": 2759,
    "totalTrades": 341,
    "lastTradedPrice": 423.0,
    "securityName": "Synergy Power Development Ltd.",
    "symbol": "SPDL"
  },
  {
    "securityId": 8066,
    "totalTrades": 335,
    "lastTradedPrice": 399.9,
    "securityName": "River Falls Power Limited",
    "symbol": "RFPL"
  },
  {
    "securityId": 385,
    "totalTrades": 331,
    "lastTradedPrice": 473.4,
    "securityName": "Asian Life Insurance Co. Limited",
    "symbol": "ALICL"
  },
  {
    "securityId": 2898,
    "totalTrades": 327,
    "lastTradedPrice": 1433.0,
    "securityName": "NRN Infrastructure and Development Limited",
    "symbol": "NRN"
  },
  {
    "securityId": 263,
    "totalTrades": 326,
    "lastTradedPrice": 481.0,
    "securityName": "Guheshowori Merchant Bank & Finance Co. Ltd.",
    "symbol": "GMFIL"
  },
  {
    "securityId": 2842,
    "totalTrades": 316,
    "lastTradedPrice": 300.0,
    "securityName": "SANJEN JALAVIDHYUT COMPANY LIMITED",
    "symbol": "SJCL"
  },
  {
    "securityId": 360,
    "totalTrades": 314,
    "lastTradedPrice": 284.9,
    "securityName": "Arun Valley Hydropower Development Co. Ltd.",
    "symbol": "AHPC"
  },
  {
    "securityId": 8055,
    "totalTrades": 311,
    "lastTradedPrice": 181.7,
    "securityName": "Balephi Hydropower Limited",
    "symbol": "BHL"
  },
  {
    "securityId": 697,
    "totalTrades": 307,
    "lastTradedPrice": 291.0,
    "securityName": "Api Power Company Ltd.",
    "symbol": "API"
  },
  {
    "securityId": 172,
    "totalTrades": 307,
    "lastTradedPrice": 1089.0,
    "securityName": "Narayani Development Bank Limited",
    "symbol": "NABBC"
  },
  {
    "securityId": 9193,
    "totalTrades": 303,
    "lastTradedPrice": 460.6,
    "securityName": "Ghorahi Cement Industry Limited",
    "symbol": "GCIL"
  },
  {
    "securityId": 9294,
    "totalTrades": 301,
    "lastTradedPrice": 1774.4,
    "securityName": "Sagar Distillery Limited",
    "symbol": "SAGAR"
  },
  {
    "securityId": 2792,
    "totalTrades": 300,
    "lastTradedPrice": 179.0,
    "securityName": "Upper Tamakoshi Hydropower Ltd",
    "symbol": "UPPER"
  },
  {
    "securityId": 139,
    "totalTrades": 293,
    "lastTradedPrice": 326.9,
    "securityName": "NIC Asia Bank Ltd.",
    "symbol": "NICA"
  },
  {
    "securityId": 9179,
    "totalTrades": 286,
    "lastTradedPrice": 296.0,
    "securityName": "Modi Energy Limited",
    "symbol": "MEL"
  },
  {
    "securityId": 133,
    "totalTrades": 285,
    "lastTradedPrice": 640.0,
    "securityName": "Standard Chartered Bank Limited",
    "symbol": "SCB"
  },
  {
    "securityId": 131,
    "totalTrades": 280,
    "lastTradedPrice": 512.5,
    "securityName": "Nabil Bank Limited",
    "symbol": "NABIL"
  },
  {
    "securityId": 142,
    "totalTrades": 273,
    "lastTradedPrice": 183.0,
    "securityName": "Kumari Bank Limited",
    "symbol": "KBL"
  },
  {
    "securityId": 8122,
    "totalTrades": 272,
    "lastTradedPrice": 341.0,
    "securityName": "People's Power Limited",
    "symbol": "PPL"
  },
  {
    "securityId": 9203,
    "totalTrades": 269,
    "lastTradedPrice": 474.8,
    "securityName": "Manakamana Engineering Hydropower Limited",
    "symbol": "MEHL"
  },
  {
    "securityId": 187,
    "totalTrades": 260,
    "lastTradedPrice": 839.2,
    "securityName": "Nepal Life Insurance Co. Ltd.",
    "symbol": "NLIC"
  },
  {
    "securityId": 9216,
    "totalTrades": 255,
    "lastTradedPrice": 433.1,
    "securityName": "Sonapur Minerals And Oil Limited",
    "symbol": "SONA"
  },
  {
    "securityId": 8070,
    "totalTrades": 254,
    "lastTradedPrice": 272.0,
    "securityName": "Dordi Khola Jal Bidyut Company Limited",
    "symbol": "DORDI"
  },
  {
    "securityId": 593,
    "totalTrades": 250,
    "lastTradedPrice": 1100.0,
    "securityName": "Kalika Laghubitta Bittiya Sanstha Ltd",
    "symbol": "KMCDB"
  },
  {
    "securityId": 2810,
    "totalTrades": 246,
    "lastTradedPrice": 369.0,
    "securityName": "UNIVERSAL POWER COMPANY LTD",
    "symbol": "UPCL"
  },
  {
    "securityId": 9184,
    "totalTrades": 245,
    "lastTradedPrice": 468.1,
    "securityName": "IME Life Insurance Company Limited",
    "symbol": "ILI"
  },
  {
    "securityId": 8131,
    "totalTrades": 245,
    "lastTradedPrice": 445.0,
    "securityName": "Eastern Hydropower Limited",
    "symbol": "EHPL"
  },
  {
    "securityId": 2934,
    "totalTrades": 243,
    "lastTradedPrice": 292.9,
    "securityName": "Singati Hydro Energy Limited",
    "symbol": "SHEL"
  },
  {
    "securityId": 2776,
    "totalTrades": 242,
    "lastTradedPrice": 738.6,
    "securityName": "Radhi Bidyut Company Ltd",
    "symbol": "RADHI"
  },
  {
    "securityId": 2757,
    "totalTrades": 240,
    "lastTradedPrice": 243.0,
    "securityName": "Arun Kabeli Power Ltd.",
    "symbol": "AKPL"
  },
  {
    "securityId": 393,
    "totalTrades": 237,
    "lastTradedPrice": 380.0,
    "securityName": "Himalayan Life Insurance Limited",
    "symbol": "HLI"
  },
  {
    "securityId": 8126,
    "totalTrades": 229,
    "lastTradedPrice": 661.0,
    "securityName": "Sikles Hydropower Limited",
    "symbol": "SIKLES"
  },
  {
    "securityId": 9209,
    "totalTrades": 228,
    "lastTradedPrice": 487.8,
    "securityName": "Citizen Life Insurance Company Limited",
    "symbol": "CLI"
  },
  {
    "securityId": 9256,
    "totalTrades": 225,
    "lastTradedPrice": 1225.0,
    "securityName": "Om Megashree Pharmaceuticals Limited",
    "symbol": "OMPL"
  },
  {
    "securityId": 2907,
    "totalTrades": 221,
    "lastTradedPrice": 165.8,
    "securityName": "Shiva Shree Hydropower Ltd",
    "symbol": "SSHL"
  },
  {
    "securityId": 2880,
    "totalTrades": 214,
    "lastTradedPrice": 184.0,
    "securityName": "Himal Dolakha Hydropower Company Limited",
    "symbol": "HDHPC"
  },
  {
    "securityId": 2766,
    "totalTrades": 212,
    "lastTradedPrice": 272.0,
    "securityName": "Chhyangdi Hydropower Ltd.",
    "symbol": "CHL"
  },
  {
    "securityId": 2767,
    "totalTrades": 212,
    "lastTradedPrice": 484.9,
    "securityName": "Himalayan Power Partner Ltd.",
    "symbol": "HPPL"
  },
  {
    "securityId": 403,
    "totalTrades": 209,
    "lastTradedPrice": 463.0,
    "securityName": "SuryaJyoti Life Insurance Company Limited",
    "symbol": "SJLIC"
  },
  {
    "securityId": 5982,
    "totalTrades": 206,
    "lastTradedPrice": 408.0,
    "securityName": "Sanima Reliance Life Insurance Limited",
    "symbol": "SRLI"
  },
  {
    "securityId": 8108,
    "totalTrades": 203,
    "lastTradedPrice": 269.9,
    "securityName": "Rapti Hydro And General Construction Limited",
    "symbol": "RHGCL"
  },
  {
    "securityId": 341,
    "totalTrades": 203,
    "lastTradedPrice": 227.5,
    "securityName": "Global IME Bank Limited",
    "symbol": "GBIME"
  },
  {
    "securityId": 2860,
    "totalTrades": 203,
    "lastTradedPrice": 829.0,
    "securityName": "Saptakoshi Development Bank Ltd",
    "symbol": "SAPDBL"
  },
  {
    "securityId": 3946,
    "totalTrades": 202,
    "lastTradedPrice": 2369.0,
    "securityName": "CEDB Holdings Limited",
    "symbol": "CHDC"
  },
  {
    "securityId": 397,
    "totalTrades": 201,
    "lastTradedPrice": 301.0,
    "securityName": "Agricultural Development Bank Limited",
    "symbol": "ADBL"
  },
  {
    "securityId": 153,
    "totalTrades": 201,
    "lastTradedPrice": 715.0,
    "securityName": "Butwal Power Company Limited",
    "symbol": "BPCL"
  },
  {
    "securityId": 8100,
    "totalTrades": 199,
    "lastTradedPrice": 416.4,
    "securityName": "Swet-Ganga Hydropower & Construction Limited ",
    "symbol": "SGHC"
  },
  {
    "securityId": 8022,
    "totalTrades": 193,
    "lastTradedPrice": 342.0,
    "securityName": "Terhathum Power Company Limited",
    "symbol": "TPC"
  },
  {
    "securityId": 8075,
    "totalTrades": 189,
    "lastTradedPrice": 485.6,
    "securityName": "Bindhyabasini Hydropower Development Company Limited",
    "symbol": "BHDC"
  },
  {
    "securityId": 141,
    "totalTrades": 188,
    "lastTradedPrice": 233.4,
    "securityName": "Laxmi Sunrise Bank Limited",
    "symbol": "LSL"
  },
  {
    "securityId": 9242,
    "totalTrades": 187,
    "lastTradedPrice": 882.8,
    "securityName": "Sarbottam Cement Limited",
    "symbol": "SARBTM"
  },
  {
    "securityId": 132,
    "totalTrades": 187,
    "lastTradedPrice": 197.0,
    "securityName": "Nepal Investment Mega Bank Limited",
    "symbol": "NIMB"
  },
  {
    "securityId": 9183,
    "totalTrades": 186,
    "lastTradedPrice": 420.4,
    "securityName": "Nepal Republic Media Limited",
    "symbol": "NRM"
  },
  {
    "securityId": 8025,
    "totalTrades": 184,
    "lastTradedPrice": 504.5,
    "securityName": "Samling Power Company Limited",
    "symbol": "SPC"
  },
  {
    "securityId": 2774,
    "totalTrades": 183,
    "lastTradedPrice": 1601.0,
    "securityName": "Unnati Sahakarya Laghubitta Bittiya Sanstha Limited",
    "symbol": "USLB"
  },
  {
    "securityId": 2742,
    "totalTrades": 183,
    "lastTradedPrice": 273.0,
    "securityName": "Hydorelectricity Investment and Development Company Ltd",
    "symbol": "HIDCL"
  },
  {
    "securityId": 610,
    "totalTrades": 179,
    "lastTradedPrice": 225.0,
    "securityName": "Ridi Power Company Limited",
    "symbol": "RIDI"
  },
  {
    "securityId": 9146,
    "totalTrades": 178,
    "lastTradedPrice": 759.0,
    "securityName": "Super Madi Hydropower Limited",
    "symbol": "SMHL"
  },
  {
    "securityId": 2903,
    "totalTrades": 176,
    "lastTradedPrice": 193.0,
    "securityName": "Liberty Energy Company Limited",
    "symbol": "LEC"
  },
  {
    "securityId": 9252,
    "totalTrades": 170,
    "lastTradedPrice": 1258.0,
    "securityName": "Crest Micro Life Insurance Limited",
    "symbol": "CREST"
  },
  {
    "securityId": 358,
    "totalTrades": 161,
    "lastTradedPrice": 450.0,
    "securityName": "Lumbini Bikas Bank Ltd.",
    "symbol": "LBBL"
  },
  {
    "securityId": 450,
    "totalTrades": 160,
    "lastTradedPrice": 1714.0,
    "securityName": "Corporate Development Bank Limited",
    "symbol": "CORBL"
  },
  {
    "securityId": 4951,
    "totalTrades": 159,
    "lastTradedPrice": 1520.0,
    "securityName": "Jeevan Bikas Laghubitta  Bittya Sanstha Ltd",
    "symbol": "JBLB"
  },
  {
    "securityId": 154,
    "totalTrades": 159,
    "lastTradedPrice": 495.1,
    "securityName": "Chilime Hydropower Company Limited",
    "symbol": "CHCL"
  },
  {
    "securityId": 2786,
    "totalTrades": 158,
    "lastTradedPrice": 338.0,
    "securityName": "Panchakanya Mai Hydropower Ltd",
    "symbol": "PMHPL"
  },
  {
    "securityId": 238,
    "totalTrades": 157,
    "lastTradedPrice": 249.8,
    "securityName": "NMB Bank Limited",
    "symbol": "NMB"
  },
  {
    "securityId": 516,
    "totalTrades": 155,
    "lastTradedPrice": 606.0,
    "securityName": "Manjushree Finance Ltd.",
    "symbol": "MFIL"
  },
  {
    "securityId": 137,
    "totalTrades": 153,
    "lastTradedPrice": 643.0,
    "securityName": "Everest Bank Limited",
    "symbol": "EBL"
  },
  {
    "securityId": 8076,
    "totalTrades": 151,
    "lastTradedPrice": 344.9,
    "securityName": "Himalayan Hydropower Limited",
    "symbol": "HHL"
  },
  {
    "securityId": 188,
    "totalTrades": 146,
    "lastTradedPrice": 901.5,
    "securityName": "Life Insurance Corporation (Nepal) Limited",
    "symbol": "LICN"
  },
  {
    "securityId": 180,
    "totalTrades": 145,
    "lastTradedPrice": 470.0,
    "securityName": "United Ajod Insurance Limited",
    "symbol": "UAIL"
  },
  {
    "securityId": 145,
    "totalTrades": 145,
    "lastTradedPrice": 355.0,
    "securityName": "Siddhartha Bank Limited",
    "symbol": "SBL"
  },
  {
    "securityId": 561,
    "totalTrades": 144,
    "lastTradedPrice": 731.0,
    "securityName": "Sindhu Bikash Bank Ltd",
    "symbol": "SINDU"
  },
  {
    "securityId": 2787,
    "totalTrades": 141,
    "lastTradedPrice": 561.0,
    "securityName": "Kalika power Company Ltd",
    "symbol": "KPCL"
  },
  {
    "securityId": 2896,
    "totalTrades": 140,
    "lastTradedPrice": 930.0,
    "securityName": "Sampada Laghubitta Bittiya Sanstha Limited",
    "symbol": "SMPDA"
  },
  {
    "securityId": 396,
    "totalTrades": 133,
    "lastTradedPrice": 684.0,
    "securityName": "Nerude Mirmire Laghubitta Bittiya Sanstha Limited",
    "symbol": "NMLBBL"
  },
  {
    "securityId": 8111,
    "totalTrades": 132,
    "lastTradedPrice": 185.0,
    "securityName": "Hydorelectricity Investment and Development Company Limited Promoter",
    "symbol": "HIDCLP"
  },
  {
    "securityId": 418,
    "totalTrades": 131,
    "lastTradedPrice": 329.2,
    "securityName": "Jyoti Bikas Bank Limited",
    "symbol": "JBBL"
  },
  {
    "securityId": 9156,
    "totalTrades": 131,
    "lastTradedPrice": 482.0,
    "securityName": "Sanima Middle Tamor Hydropower Limited",
    "symbol": "TAMOR"
  },
  {
    "securityId": 2806,
    "totalTrades": 130,
    "lastTradedPrice": 213.3,
    "securityName": "Ghalemdi Hydro Limited",
    "symbol": "GHL"
  },
  {
    "securityId": 171,
    "totalTrades": 128,
    "lastTradedPrice": 315.0,
    "securityName": "Sanima Bank Limited",
    "symbol": "SANIMA"
  },
  {
    "securityId": 2924,
    "totalTrades": 123,
    "lastTradedPrice": 255.8,
    "securityName": "GreenLife Hydropower Limited",
    "symbol": "GLH"
  },
  {
    "securityId": 9250,
    "totalTrades": 122,
    "lastTradedPrice": 1289.0,
    "securityName": "Nepal Micro Insurance Company Limited",
    "symbol": "NMIC"
  },
  {
    "securityId": 574,
    "totalTrades": 122,
    "lastTradedPrice": 873.0,
    "securityName": "Sana Kisan Bikas Laghubitta Bittiya Sanstha Limited",
    "symbol": "SKBBL"
  },
  {
    "securityId": 472,
    "totalTrades": 120,
    "lastTradedPrice": 413.9,
    "securityName": "Shangrila Development Bank Ltd.",
    "symbol": "SADBL"
  },
  {
    "securityId": 9213,
    "totalTrades": 120,
    "lastTradedPrice": 918.5,
    "securityName": "Hathway Investment Nepal Limited",
    "symbol": "HATHY"
  },
  {
    "securityId": 9300,
    "totalTrades": 120,
    "lastTradedPrice": 976.0,
    "securityName": "Jhapa Energy Limited",
    "symbol": "JHAPA"
  },
  {
    "securityId": 9159,
    "totalTrades": 119,
    "lastTradedPrice": 520.0,
    "securityName": "Sagarmatha Jalabidhyut Company Limited",
    "symbol": "SMJC"
  },
  {
    "securityId": 517,
    "totalTrades": 119,
    "lastTradedPrice": 243.0,
    "securityName": "Nepal Bank Limited",
    "symbol": "NBL"
  },
  {
    "securityId": 473,
    "totalTrades": 119,
    "lastTradedPrice": 394.5,
    "securityName": "Shine Resunga Development Bank Ltd.",
    "symbol": "SHINE"
  },
  {
    "securityId": 2788,
    "totalTrades": 118,
    "lastTradedPrice": 188.3,
    "securityName": "Ankhu Khola Jalvidhyut Company Ltd",
    "symbol": "AKJCL"
  },
  {
    "securityId": 2824,
    "totalTrades": 116,
    "lastTradedPrice": 227.5,
    "securityName": "Himalaya Urja Bikas Company Limited",
    "symbol": "HURJA"
  },
  {
    "securityId": 2908,
    "totalTrades": 111,
    "lastTradedPrice": 489.0,
    "securityName": "Sanima GIC Insurance Limited",
    "symbol": "SGIC"
  },
  {
    "securityId": 9171,
    "totalTrades": 111,
    "lastTradedPrice": 560.0,
    "securityName": "Bhugol Energy Development Company Limited",
    "symbol": "BEDC"
  },
  {
    "securityId": 2915,
    "totalTrades": 110,
    "lastTradedPrice": 508.9,
    "securityName": "Prabhu Mahalaxmi Life Insurance Limited",
    "symbol": "PMLI"
  },
  {
    "securityId": 194,
    "totalTrades": 109,
    "lastTradedPrice": 640.0,
    "securityName": "Nepal Finance Ltd.",
    "symbol": "NFS"
  },
  {
    "securityId": 474,
    "totalTrades": 106,
    "lastTradedPrice": 351.0,
    "securityName": "Muktinath Bikas Bank Ltd.",
    "symbol": "MNBBL"
  },
  {
    "securityId": 236,
    "totalTrades": 106,
    "lastTradedPrice": 370.5,
    "securityName": "Pokhara Finance Ltd.",
    "symbol": "PFL"
  },
  {
    "securityId": 164,
    "totalTrades": 104,
    "lastTradedPrice": 1032.2,
    "securityName": "Chhimek Laghubitta Bittiya Sanstha Limited",
    "symbol": "CBBL"
  },
  {
    "securityId": 2917,
    "totalTrades": 104,
    "lastTradedPrice": 879.8,
    "securityName": "Chandragiri Hills Limited",
    "symbol": "CGH"
  },
  {
    "securityId": 417,
    "totalTrades": 104,
    "lastTradedPrice": 381.0,
    "securityName": "Garima Bikas Bank Limited",
    "symbol": "GBBL"
  },
  {
    "securityId": 152,
    "totalTrades": 102,
    "lastTradedPrice": 191.9,
    "securityName": "National Hydro Power Company Limited",
    "symbol": "NHPC"
  },
  {
    "securityId": 2754,
    "totalTrades": 101,
    "lastTradedPrice": 305.1,
    "securityName": "Dibyashwori Hydropower Ltd.",
    "symbol": "DHPL"
  },
  {
    "securityId": 8102,
    "totalTrades": 100,
    "lastTradedPrice": 496.5,
    "securityName": "Mandakini Hydropower Limited",
    "symbol": "MHL"
  },
  {
    "securityId": 490,
    "totalTrades": 99,
    "lastTradedPrice": 830.5,
    "securityName": "First Micro Finance Laghubitta Bittiya Sanstha Limited",
    "symbol": "FMDBL"
  },
  {
    "securityId": 401,
    "totalTrades": 99,
    "lastTradedPrice": 383.9,
    "securityName": "Mahalaxmi Bikas Bank Ltd.",
    "symbol": "MLBL"
  },
  {
    "securityId": 178,
    "totalTrades": 97,
    "lastTradedPrice": 612.5,
    "securityName": "National Life Insurance Co. Ltd.",
    "symbol": "NLICL"
  },
  {
    "securityId": 307,
    "totalTrades": 97,
    "lastTradedPrice": 860.0,
    "securityName": "Nepal Doorsanchar Company Limited",
    "symbol": "NTC"
  },
  {
    "securityId": 357,
    "totalTrades": 94,
    "lastTradedPrice": 248.4,
    "securityName": "Prime Commercial Bank Ltd.",
    "symbol": "PCBL"
  },
  {
    "securityId": 2813,
    "totalTrades": 94,
    "lastTradedPrice": 334.5,
    "securityName": "Panchthar Power Compant Limited",
    "symbol": "PPCL"
  },
  {
    "securityId": 9208,
    "totalTrades": 94,
    "lastTradedPrice": 457.0,
    "securityName": "Upper Lohore Khola Hydropower Company Limited",
    "symbol": "ULHC"
  },
  {
    "securityId": 8104,
    "totalTrades": 92,
    "lastTradedPrice": 478.5,
    "securityName": "Upper Solu Hydro Electric Company Limited",
    "symbol": "USHEC"
  },
  {
    "securityId": 8099,
    "totalTrades": 91,
    "lastTradedPrice": 605.0,
    "securityName": "Upper Hewakhola Hydropower Company Limited",
    "symbol": "UHEWA"
  },
  {
    "securityId": 250,
    "totalTrades": 91,
    "lastTradedPrice": 422.1,
    "securityName": "Janaki Finance Company Limited",
    "symbol": "JFL"
  },
  {
    "securityId": 9170,
    "totalTrades": 90,
    "lastTradedPrice": 535.0,
    "securityName": "Dolti Power Company Limited",
    "symbol": "DOLTI"
  },
  {
    "securityId": 8005,
    "totalTrades": 90,
    "lastTradedPrice": 536.5,
    "securityName": "Mailung Khola Jal Vidhyut Company Limited",
    "symbol": "MKJC"
  },
  {
    "securityId": 8026,
    "totalTrades": 87,
    "lastTradedPrice": 400.2,
    "securityName": "Nyadi Hydropower Limited",
    "symbol": "NYADI"
  },
  {
    "securityId": 9151,
    "totalTrades": 84,
    "lastTradedPrice": 884.0,
    "securityName": "Kalinchowk Darshan Limited",
    "symbol": "KDL"
  },
  {
    "securityId": 2761,
    "totalTrades": 83,
    "lastTradedPrice": 821.0,
    "securityName": "Samata Gharelu Laghubitta Bittiya Sanstha Limited",
    "symbol": "SMATA"
  },
  {
    "securityId": 176,
    "totalTrades": 82,
    "lastTradedPrice": 526.0,
    "securityName": "Nepal Insurance Co. Ltd.",
    "symbol": "NICL"
  },
  {
    "securityId": 348,
    "totalTrades": 81,
    "lastTradedPrice": 193.1,
    "securityName": "Citizens Bank International Limited",
    "symbol": "CZBIL"
  },
  {
    "securityId": 9301,
    "totalTrades": 81,
    "lastTradedPrice": 587.4,
    "securityName": "Shreenagar Agritech Industries Limited",
    "symbol": "SAIL"
  },
  {
    "securityId": 2832,
    "totalTrades": 80,
    "lastTradedPrice": 1127.0,
    "securityName": "Infinity Laghubitta Bittiya Sanstha Limited",
    "symbol": "ILBS"
  },
  {
    "securityId": 140,
    "totalTrades": 79,
    "lastTradedPrice": 220.8,
    "securityName": "Machhapuchhre Bank Limited",
    "symbol": "MBL"
  },
  {
    "securityId": 471,
    "totalTrades": 78,
    "lastTradedPrice": 552.6,
    "securityName": "Multipurpose Finance Company  Limited",
    "symbol": "MPFL"
  },
  {
    "securityId": 9212,
    "totalTrades": 78,
    "lastTradedPrice": 814.0,
    "securityName": "Mandu Hydropower Limited",
    "symbol": "MANDU"
  },
  {
    "securityId": 8032,
    "totalTrades": 77,
    "lastTradedPrice": 445.3,
    "securityName": "Buddha Bhumi Nepal Hydropower Company Limited",
    "symbol": "BNHC"
  },
  {
    "securityId": 166,
    "totalTrades": 76,
    "lastTradedPrice": 889.8,
    "securityName": "Deprosc Laghubitta Bittiya Sanstha Limited",
    "symbol": "DDBL"
  },
  {
    "securityId": 256,
    "totalTrades": 76,
    "lastTradedPrice": 396.0,
    "securityName": "Samriddhi Finance Company Limited",
    "symbol": "SFCL"
  },
  {
    "securityId": 371,
    "totalTrades": 74,
    "lastTradedPrice": 573.0,
    "securityName": "Miteri Development Bank Limited",
    "symbol": "MDB"
  },
  {
    "securityId": 9225,
    "totalTrades": 74,
    "lastTradedPrice": 568.9,
    "securityName": "Vision Lumbini Urja Company Limited ",
    "symbol": "VLUCL"
  },
  {
    "securityId": 9217,
    "totalTrades": 73,
    "lastTradedPrice": 589.9,
    "securityName": "Mathillo Mailun Khola Jalvidhyut Limited",
    "symbol": "MMKJL"
  },
  {
    "securityId": 183,
    "totalTrades": 72,
    "lastTradedPrice": 625.0,
    "securityName": "Neco Insurance Limited",
    "symbol": "NIL"
  },
  {
    "securityId": 135,
    "totalTrades": 72,
    "lastTradedPrice": 397.3,
    "securityName": "Nepal SBI Bank Limited",
    "symbol": "SBI"
  },
  {
    "securityId": 559,
    "totalTrades": 71,
    "lastTradedPrice": 707.0,
    "securityName": "NLG Insurance Company Ltd.",
    "symbol": "NLG"
  },
  {
    "securityId": 186,
    "totalTrades": 70,
    "lastTradedPrice": 426.0,
    "securityName": "IGI Prudential insurance Limited",
    "symbol": "IGI"
  },
  {
    "securityId": 2887,
    "totalTrades": 70,
    "lastTradedPrice": 579.0,
    "securityName": "NIC ASIA Laghubitta Bittiya Sanstha Limited",
    "symbol": "NICLBSL"
  },
  {
    "securityId": 163,
    "totalTrades": 69,
    "lastTradedPrice": 776.0,
    "securityName": "Nirdhan Utthan Laghubitta Bittiya Sanstha Limited",
    "symbol": "NUBL"
  },
  {
    "securityId": 9218,
    "totalTrades": 69,
    "lastTradedPrice": 420.0,
    "securityName": "Trishuli Jal Vidhyut Company Limited ",
    "symbol": "TVCL"
  },
  {
    "securityId": 210,
    "totalTrades": 69,
    "lastTradedPrice": 1862.0,
    "securityName": "Citizen Investment Trust",
    "symbol": "CIT"
  },
  {
    "securityId": 9147,
    "totalTrades": 68,
    "lastTradedPrice": 915.1,
    "securityName": "Shuvam Power Limited",
    "symbol": "SPL"
  },
  {
    "securityId": 2811,
    "totalTrades": 68,
    "lastTradedPrice": 253.0,
    "securityName": "Mountain Hydro Nepal Limited",
    "symbol": "MHNL"
  },
  {
    "securityId": 9149,
    "totalTrades": 67,
    "lastTradedPrice": 394.9,
    "securityName": "Maya Khola Hydropower Company Limited",
    "symbol": "MKHC"
  },
  {
    "securityId": 9167,
    "totalTrades": 65,
    "lastTradedPrice": 807.0,
    "securityName": "Mai Khola Hydropower Limited",
    "symbol": "MKHL"
  },
  {
    "securityId": 2748,
    "totalTrades": 65,
    "lastTradedPrice": 659.0,
    "securityName": "RSDC Laghubitta Bittiya Sanstha Ltd.",
    "symbol": "RSDC"
  },
  {
    "securityId": 184,
    "totalTrades": 64,
    "lastTradedPrice": 683.1,
    "securityName": "Prabhu Insurance Ltd.",
    "symbol": "PRIN"
  },
  {
    "securityId": 545,
    "totalTrades": 63,
    "lastTradedPrice": 910.5,
    "securityName": "Swarojgar Laghubitta Bittiya Sanstha Ltd.",
    "symbol": "SLBBL"
  },
  {
    "securityId": 2935,
    "totalTrades": 63,
    "lastTradedPrice": 748.0,
    "securityName": "Ru Ru Jalbidhyut Pariyojana Limited",
    "symbol": "RURU"
  },
  {
    "securityId": 9158,
    "totalTrades": 62,
    "lastTradedPrice": 399.1,
    "securityName": "Molung Hydropower Company Limited",
    "symbol": "MHCL"
  },
  {
    "securityId": 227,
    "totalTrades": 60,
    "lastTradedPrice": 475.3,
    "securityName": "Best Finance Company Ltd.",
    "symbol": "BFC"
  },
  {
    "securityId": 244,
    "totalTrades": 60,
    "lastTradedPrice": 511.0,
    "securityName": "Shree Investment Finance Co. Ltd.",
    "symbol": "SIFC"
  },
  {
    "securityId": 9230,
    "totalTrades": 58,
    "lastTradedPrice": 1385.0,
    "securityName": "Muktinath Krishi Company Limited",
    "symbol": "MKCL"
  },
  {
    "securityId": 2914,
    "totalTrades": 58,
    "lastTradedPrice": 577.0,
    "securityName": "United IDI Mardi RB Hydropower Limited.",
    "symbol": "UMRH"
  },
  {
    "securityId": 9176,
    "totalTrades": 57,
    "lastTradedPrice": 552.9,
    "securityName": "Ingwa Hydropower Limited",
    "symbol": "IHL"
  },
  {
    "securityId": 2771,
    "totalTrades": 57,
    "lastTradedPrice": 2154.0,
    "securityName": "Support Microfinance Bittiya Sanstha Ltd.",
    "symbol": "SMB"
  },
  {
    "securityId": 587,
    "totalTrades": 56,
    "lastTradedPrice": 432.0,
    "securityName": "Reliance Finance Ltd.",
    "symbol": "RLFL"
  },
  {
    "securityId": 9173,
    "totalTrades": 56,
    "lastTradedPrice": 531.2,
    "securityName": "City Hotel Limited",
    "symbol": "CITY"
  },
  {
    "securityId": 9192,
    "totalTrades": 55,
    "lastTradedPrice": 698.0,
    "securityName": "Upper Syange Hydropower Limited",
    "symbol": "USHL"
  },
  {
    "securityId": 147,
    "totalTrades": 55,
    "lastTradedPrice": 487.4,
    "securityName": "Soaltee Hotel Limited",
    "symbol": "SHL"
  },
  {
    "securityId": 2768,
    "totalTrades": 54,
    "lastTradedPrice": 1480.0,
    "securityName": "Mahuli Laghubitta Bittiya Sanstha Limited",
    "symbol": "MSLB"
  },
  {
    "securityId": 268,
    "totalTrades": 54,
    "lastTradedPrice": 807.0,
    "securityName": "Swabalamban Laghubitta Bittiya Sanstha Limited",
    "symbol": "SWBBL"
  },
  {
    "securityId": 182,
    "totalTrades": 53,
    "lastTradedPrice": 721.0,
    "securityName": "Siddhartha Premier Insurance Limited",
    "symbol": "SPIL"
  },
  {
    "securityId": 1741,
    "totalTrades": 53,
    "lastTradedPrice": 775.0,
    "securityName": "Mero Microfinance Bittiya Sanstha Ltd.",
    "symbol": "MERO"
  },
  {
    "securityId": 9233,
    "totalTrades": 53,
    "lastTradedPrice": 819.1,
    "securityName": "Nepal Warehousing Company Limited ",
    "symbol": "NWCL"
  },
  {
    "securityId": 245,
    "totalTrades": 51,
    "lastTradedPrice": 494.7,
    "securityName": "Central Finance Co. Ltd.",
    "symbol": "CFCL"
  },
  {
    "securityId": 9215,
    "totalTrades": 51,
    "lastTradedPrice": 907.0,
    "securityName": "Mid Solu Hydropower Limited",
    "symbol": "MSHL"
  },
  {
    "securityId": 338,
    "totalTrades": 50,
    "lastTradedPrice": 464.9,
    "securityName": "Progressive Finance Limited",
    "symbol": "PROFL"
  },
  {
    "securityId": 274,
    "totalTrades": 50,
    "lastTradedPrice": 586.3,
    "securityName": "Excel Development Bank Ltd.",
    "symbol": "EDBL"
  },
  {
    "securityId": 9194,
    "totalTrades": 50,
    "lastTradedPrice": 698.0,
    "securityName": "Three Star Hydropower Limited",
    "symbol": "TSHL"
  },
  {
    "securityId": 273,
    "totalTrades": 49,
    "lastTradedPrice": 646.8,
    "securityName": "ICFC Finance Limited",
    "symbol": "ICFC"
  },
  {
    "securityId": 8121,
    "totalTrades": 49,
    "lastTradedPrice": 537.0,
    "securityName": "Sayapatri Hydropower Limited",
    "symbol": "SPHL"
  },
  {
    "securityId": 459,
    "totalTrades": 48,
    "lastTradedPrice": 437.0,
    "securityName": "Kamana Sewa Bikas Bank Limited",
    "symbol": "KSBBL"
  },
  {
    "securityId": 149,
    "totalTrades": 48,
    "lastTradedPrice": 716.0,
    "securityName": "Oriental Hotels Limited",
    "symbol": "OHL"
  },
  {
    "securityId": 9246,
    "totalTrades": 47,
    "lastTradedPrice": 1825.1,
    "securityName": "Guardian Micro Life Insurance Limited ",
    "symbol": "GMLI"
  },
  {
    "securityId": 8023,
    "totalTrades": 46,
    "lastTradedPrice": 8.67,
    "securityName": "Mega Mutual Fund -1",
    "symbol": "MMF1"
  },
  {
    "securityId": 9175,
    "totalTrades": 45,
    "lastTradedPrice": 487.0,
    "securityName": "Menchhiyam Hydropower Limited",
    "symbol": "MCHL"
  },
  {
    "securityId": 8065,
    "totalTrades": 44,
    "lastTradedPrice": 1537.0,
    "securityName": "CYC Nepal Laghubitta Bittiya Sanstha Limited",
    "symbol": "CYCL"
  },
  {
    "securityId": 9232,
    "totalTrades": 44,
    "lastTradedPrice": 639.0,
    "securityName": "Chirkhwa Hydropower Limited ",
    "symbol": "CKHL"
  },
  {
    "securityId": 2751,
    "totalTrades": 44,
    "lastTradedPrice": 247.0,
    "securityName": "Khanikhola Hydropower Co. Ltd.",
    "symbol": "KKHC"
  },
  {
    "securityId": 693,
    "totalTrades": 43,
    "lastTradedPrice": 925.0,
    "securityName": "Himalayan Laghubitta Bittiya Sanstha Limited",
    "symbol": "HLBSL"
  },
  {
    "securityId": 192,
    "totalTrades": 42,
    "lastTradedPrice": 653.0,
    "securityName": "Shikhar Insurance Co. Ltd.",
    "symbol": "SICL"
  },
  {
    "securityId": 9135,
    "totalTrades": 41,
    "lastTradedPrice": 662.0,
    "securityName": "Barahi Hydropower Public Limited",
    "symbol": "BHPL"
  },
  {
    "securityId": 9166,
    "totalTrades": 41,
    "lastTradedPrice": 550.1,
    "securityName": "Makar Jitumaya Suri Hydropower Limited",
    "symbol": "MAKAR"
  },
  {
    "securityId": 8117,
    "totalTrades": 40,
    "lastTradedPrice": 990.0,
    "securityName": "Aviyan Laghubitta Bittiya Sanstha Limited",
    "symbol": "AVYAN"
  },
  {
    "securityId": 9181,
    "totalTrades": 40,
    "lastTradedPrice": 705.6,
    "securityName": "Rawa Energy Development Limited",
    "symbol": "RAWA"
  },
  {
    "securityId": 232,
    "totalTrades": 38,
    "lastTradedPrice": 592.0,
    "securityName": "Goodwill Finance Limited",
    "symbol": "GFCL"
  },
  {
    "securityId": 2746,
    "totalTrades": 37,
    "lastTradedPrice": 1300.0,
    "securityName": "National Laghubitta Bittiya Sanstha Limited",
    "symbol": "NMFBS"
  },
  {
    "securityId": 185,
    "totalTrades": 36,
    "lastTradedPrice": 609.0,
    "securityName": "Sagarmatha Lumbini Insurance Co. Limited",
    "symbol": "SALICO"
  },
  {
    "securityId": 9248,
    "totalTrades": 36,
    "lastTradedPrice": 9.05,
    "securityName": "Garima Samriddhi Yojana",
    "symbol": "GSY"
  },
  {
    "securityId": 179,
    "totalTrades": 34,
    "lastTradedPrice": 500.0,
    "securityName": "Himalayan Everest Insurance Limited",
    "symbol": "HEI"
  },
  {
    "securityId": 706,
    "totalTrades": 34,
    "lastTradedPrice": 702.0,
    "securityName": "Suryodaya Womi Laghubitta Bittiya Sanstha Limited",
    "symbol": "SWMF"
  },
  {
    "securityId": 148,
    "totalTrades": 31,
    "lastTradedPrice": 709.9,
    "securityName": "Taragaon Regency Hotel Limited",
    "symbol": "TRH"
  },
  {
    "securityId": 2769,
    "totalTrades": 31,
    "lastTradedPrice": 696.0,
    "securityName": "Nepal Hydro Developers Ltd.",
    "symbol": "NHDL"
  },
  {
    "securityId": 9214,
    "totalTrades": 30,
    "lastTradedPrice": 768.0,
    "securityName": "Bhagawati Hydropower Development Company Limited",
    "symbol": "BGWT"
  },
  {
    "securityId": 8123,
    "totalTrades": 30,
    "lastTradedPrice": 1368.0,
    "securityName": "Dhaulagiri Laghubitta Bittiya Sanstha Limited",
    "symbol": "DLBS"
  },
  {
    "securityId": 8063,
    "totalTrades": 29,
    "lastTradedPrice": 3769.0,
    "securityName": "Upakar Laghubitta Bittiya Sanstha Limited",
    "symbol": "ULBSL"
  },
  {
    "securityId": 8074,
    "totalTrades": 29,
    "lastTradedPrice": 9.37,
    "securityName": "Kumari Dhanabriddhi Yojana",
    "symbol": "KDBY"
  },
  {
    "securityId": 687,
    "totalTrades": 29,
    "lastTradedPrice": 790.9,
    "securityName": "Vijaya laghubitta Bittiya Sanstha Ltd.",
    "symbol": "VLBS"
  },
  {
    "securityId": 9150,
    "totalTrades": 28,
    "lastTradedPrice": 600.0,
    "securityName": "Asian Hydropower Limited",
    "symbol": "AHL"
  },
  {
    "securityId": 704,
    "totalTrades": 28,
    "lastTradedPrice": 703.0,
    "securityName": "NMB  Microfinance Bittiya Sanstha Ltd.",
    "symbol": "NMBMF"
  },
  {
    "securityId": 2923,
    "totalTrades": 27,
    "lastTradedPrice": 9.0,
    "securityName": "Sanima Large Cap Fund",
    "symbol": "SLCF"
  },
  {
    "securityId": 601,
    "totalTrades": 27,
    "lastTradedPrice": 1510.0,
    "securityName": "Mithila LaghuBitta Bittiya Sanstha Limited",
    "symbol": "MLBBL"
  },
  {
    "securityId": 8041,
    "totalTrades": 26,
    "lastTradedPrice": 1515.5,
    "securityName": "NESDO Sambridha Laghubitta Bittiya Sanstha Limited",
    "symbol": "NESDO"
  },
  {
    "securityId": 2804,
    "totalTrades": 26,
    "lastTradedPrice": 1305.0,
    "securityName": "Samudayik Laghubitta Bittiya Sanstha Limited",
    "symbol": "SLBSL"
  },
  {
    "securityId": 2758,
    "totalTrades": 25,
    "lastTradedPrice": 1120.0,
    "securityName": "Forward Microfinance Laghubitta Bittiya Sanstha Limited",
    "symbol": "FOWAD"
  },
  {
    "securityId": 2781,
    "totalTrades": 25,
    "lastTradedPrice": 1975.0,
    "securityName": "Wean Nepal Laghubitta Bittiya Sanstha Limited",
    "symbol": "WNLB"
  },
  {
    "securityId": 705,
    "totalTrades": 24,
    "lastTradedPrice": 1287.5,
    "securityName": "Global IME Laghubitta Bittiya Sanstha Ltd.",
    "symbol": "GILB"
  },
  {
    "securityId": 9257,
    "totalTrades": 24,
    "lastTradedPrice": 9.05,
    "securityName": "MBL Equity Fund",
    "symbol": "MBLEF"
  },
  {
    "securityId": 8034,
    "totalTrades": 24,
    "lastTradedPrice": 934.0,
    "securityName": "Emerging Nepal Limited",
    "symbol": "ENL"
  },
  {
    "securityId": 2790,
    "totalTrades": 22,
    "lastTradedPrice": 1015.5,
    "securityName": "Aarambha Chautari Laghubitta Bittiya Sanstha Limited",
    "symbol": "ACLBSL"
  },
  {
    "securityId": 177,
    "totalTrades": 22,
    "lastTradedPrice": 15245.0,
    "securityName": "Rastriya Beema Company Limited",
    "symbol": "RBCL"
  },
  {
    "securityId": 2829,
    "totalTrades": 22,
    "lastTradedPrice": 1680.0,
    "securityName": "Swabhimaan Laghubitta Bittiya Sanstha Limited",
    "symbol": "SMFBS"
  },
  {
    "securityId": 9269,
    "totalTrades": 22,
    "lastTradedPrice": 8.82,
    "securityName": "Global IME Sammunat Yojana -2",
    "symbol": "GBIMESY2"
  },
  {
    "securityId": 9259,
    "totalTrades": 22,
    "lastTradedPrice": 9.18,
    "securityName": "Reliable Samriddhi Yojana",
    "symbol": "RSY"
  },
  {
    "securityId": 9174,
    "totalTrades": 21,
    "lastTradedPrice": 10.45,
    "securityName": "Prabhu Smart Fund",
    "symbol": "PRSF"
  },
  {
    "securityId": 8132,
    "totalTrades": 20,
    "lastTradedPrice": 1729.0,
    "securityName": "Shrijanshil Laghubitta Bittiya Sanstha Limited",
    "symbol": "SHLB"
  },
  {
    "securityId": 8018,
    "totalTrades": 20,
    "lastTradedPrice": 1496.3,
    "securityName": "Manushi Laghubitta Bittiya Sanstha Limited",
    "symbol": "MLBS"
  },
  {
    "securityId": 8024,
    "totalTrades": 19,
    "lastTradedPrice": 9.03,
    "securityName": "Nabil Balanced Fund-3",
    "symbol": "NBF3"
  },
  {
    "securityId": 9290,
    "totalTrades": 19,
    "lastTradedPrice": 9.09,
    "securityName": "HLI Large Cap Fund",
    "symbol": "HLICF"
  },
  {
    "securityId": 2925,
    "totalTrades": 19,
    "lastTradedPrice": 2000.0,
    "securityName": "Mahila Lagubitta Bittiya Sanstha Limited ",
    "symbol": "MLBSL"
  },
  {
    "securityId": 204,
    "totalTrades": 19,
    "lastTradedPrice": 508.9,
    "securityName": "Gurkhas Finance Ltd.",
    "symbol": "GUFL"
  },
  {
    "securityId": 2784,
    "totalTrades": 19,
    "lastTradedPrice": 772.3,
    "securityName": "Nadep Laghubittiya bittya Sanstha Ltd.",
    "symbol": "NADEP"
  },
  {
    "securityId": 9244,
    "totalTrades": 19,
    "lastTradedPrice": 8.41,
    "securityName": "NIBL Stable Fund",
    "symbol": "NIBLSTF"
  },
  {
    "securityId": 9245,
    "totalTrades": 19,
    "lastTradedPrice": 8.87,
    "securityName": "Muktinath Mutual Fund 1",
    "symbol": "MNMF1"
  },
  {
    "securityId": 2933,
    "totalTrades": 18,
    "lastTradedPrice": 9.09,
    "securityName": "Kumari Equity Fund",
    "symbol": "KEF"
  },
  {
    "securityId": 213,
    "totalTrades": 18,
    "lastTradedPrice": 12100.0,
    "securityName": "Bottlers Nepal (Terai) Limited",
    "symbol": "BNT"
  },
  {
    "securityId": 4968,
    "totalTrades": 18,
    "lastTradedPrice": 9.17,
    "securityName": "RBB Mutual Fund 1",
    "symbol": "RMF1"
  },
  {
    "securityId": 4947,
    "totalTrades": 17,
    "lastTradedPrice": 10.55,
    "securityName": "Prabhu Select Fund",
    "symbol": "PSF"
  },
  {
    "securityId": 155,
    "totalTrades": 17,
    "lastTradedPrice": 5360.0,
    "securityName": "Salt Trading Corporation",
    "symbol": "STC"
  },
  {
    "securityId": 4967,
    "totalTrades": 17,
    "lastTradedPrice": 8.5,
    "securityName": "NIC Asia Select Fund 30",
    "symbol": "NICSF"
  },
  {
    "securityId": 2815,
    "totalTrades": 16,
    "lastTradedPrice": 1564.0,
    "securityName": "Ganapati Laghubitta Bittiya Sanstha Limited",
    "symbol": "GMFBS"
  },
  {
    "securityId": 8106,
    "totalTrades": 16,
    "lastTradedPrice": 10.1,
    "securityName": "Global IME Balanced Fund-1",
    "symbol": "GIBF1"
  },
  {
    "securityId": 9221,
    "totalTrades": 16,
    "lastTradedPrice": 10.55,
    "securityName": "Himalayan 80-20",
    "symbol": "H8020"
  },
  {
    "securityId": 694,
    "totalTrades": 16,
    "lastTradedPrice": 953.2,
    "securityName": "Matribhumi Lagubitta Bittiya Sanstha Limited",
    "symbol": "MATRI"
  },
  {
    "securityId": 9261,
    "totalTrades": 16,
    "lastTradedPrice": 1070.0,
    "securityName": "Nifra Green Energy Debenture 6% - 2088/89",
    "symbol": "NIFRAGED"
  },
  {
    "securityId": 9148,
    "totalTrades": 15,
    "lastTradedPrice": 790.0,
    "securityName": "Super Mai Hydropower Limited",
    "symbol": "SMH"
  },
  {
    "securityId": 2826,
    "totalTrades": 15,
    "lastTradedPrice": 2000.0,
    "securityName": "Gurans Laghubitta Bittiya Sanstha Limited",
    "symbol": "GLBSL"
  },
  {
    "securityId": 2835,
    "totalTrades": 15,
    "lastTradedPrice": 9.27,
    "securityName": "NABIL BALANCED FUND-2",
    "symbol": "NBF2"
  },
  {
    "securityId": 2877,
    "totalTrades": 15,
    "lastTradedPrice": 9.99,
    "securityName": "Sunrise First Mutual Fund",
    "symbol": "SFMF"
  },
  {
    "securityId": 9191,
    "totalTrades": 14,
    "lastTradedPrice": 9.28,
    "securityName": "Citizens Super 30 Mutual Fund",
    "symbol": "C30MF"
  },
  {
    "securityId": 9254,
    "totalTrades": 14,
    "lastTradedPrice": 8.96,
    "securityName": "NMB Hybrid Fund L- II",
    "symbol": "NMBHF2"
  },
  {
    "securityId": 618,
    "totalTrades": 12,
    "lastTradedPrice": 1025.9,
    "securityName": "Laxmi Laghubitta Bittiya Sanstha Ltd.",
    "symbol": "LLBS"
  },
  {
    "securityId": 9286,
    "totalTrades": 12,
    "lastTradedPrice": 1151.1,
    "securityName": "Shine Resunga Debenture",
    "symbol": "SHINED"
  },
  {
    "securityId": 2902,
    "totalTrades": 11,
    "lastTradedPrice": 9.25,
    "securityName": "Laxmi Unnati Kosh",
    "symbol": "LUK"
  },
  {
    "securityId": 8073,
    "totalTrades": 11,
    "lastTradedPrice": 8.77,
    "securityName": "NIC Asia Flexi CAP Fund",
    "symbol": "NICFC"
  },
  {
    "securityId": 9196,
    "totalTrades": 10,
    "lastTradedPrice": 1800.0,
    "securityName": "Kutheli Bukhari Small Hydropower Limited",
    "symbol": "KBSH"
  },
  {
    "securityId": 156,
    "totalTrades": 9,
    "lastTradedPrice": 4938.0,
    "securityName": "Bishal Bazar Company Limited",
    "symbol": "BBC"
  },
  {
    "securityId": 9178,
    "totalTrades": 8,
    "lastTradedPrice": 9.27,
    "securityName": "RBB Mutual Fund 2",
    "symbol": "RMF2"
  },
  {
    "securityId": 8125,
    "totalTrades": 8,
    "lastTradedPrice": 10.12,
    "securityName": "NMB Sulav Investment Fund - 2",
    "symbol": "NSIF2"
  },
  {
    "securityId": 695,
    "totalTrades": 8,
    "lastTradedPrice": 1220.0,
    "securityName": "Janautthan Samudayic Laghubitta Bittya Sanstha Limited",
    "symbol": "JSLBB"
  },
  {
    "securityId": 700,
    "totalTrades": 7,
    "lastTradedPrice": 327.0,
    "securityName": "Himalayan Everest Insurance Limited Promoter",
    "symbol": "HEIP"
  },
  {
    "securityId": 2770,
    "totalTrades": 7,
    "lastTradedPrice": 9.2,
    "securityName": "Siddhartha Equity Fund",
    "symbol": "SEF"
  },
  {
    "securityId": 9182,
    "totalTrades": 7,
    "lastTradedPrice": 9.38,
    "securityName": "Siddhartha Investment Growth Scheme 3",
    "symbol": "SIGS3"
  },
  {
    "securityId": 9154,
    "totalTrades": 7,
    "lastTradedPrice": 9.2,
    "securityName": "Sunrise Focused Equity Fund",
    "symbol": "SFEF"
  },
  {
    "securityId": 9138,
    "totalTrades": 7,
    "lastTradedPrice": 8.4,
    "securityName": "NIBL Growth Fund",
    "symbol": "NIBLGF"
  },
  {
    "securityId": 9236,
    "totalTrades": 7,
    "lastTradedPrice": 8.78,
    "securityName": "NIC ASIA Growth Fund-2",
    "symbol": "NICGF2"
  },
  {
    "securityId": 9139,
    "totalTrades": 7,
    "lastTradedPrice": 9.48,
    "securityName": "Sanima Growth Fund",
    "symbol": "SAGF"
  },
  {
    "securityId": 9295,
    "totalTrades": 7,
    "lastTradedPrice": 1085.8,
    "securityName": "Swastik Laghubitta Bittiya Sanstha Limited",
    "symbol": "SWASTIK"
  },
  {
    "securityId": 4949,
    "totalTrades": 6,
    "lastTradedPrice": 8.39,
    "securityName": "NIBL Samriddhi Fund -2",
    "symbol": "NIBSF2"
  },
  {
    "securityId": 2937,
    "totalTrades": 6,
    "lastTradedPrice": 9.15,
    "securityName": "Sunrise Bluechip Fund",
    "symbol": "SBCF"
  },
  {
    "securityId": 469,
    "totalTrades": 6,
    "lastTradedPrice": 163.8,
    "securityName": "Nepal Investment Mega Bank Ltd. Promoter Share",
    "symbol": "NIMBPO"
  },
  {
    "securityId": 9140,
    "totalTrades": 5,
    "lastTradedPrice": 2005.0,
    "securityName": "Unique Nepal Laghubitta Bittiya Sanstha Limited",
    "symbol": "UNLB"
  },
  {
    "securityId": 2859,
    "totalTrades": 5,
    "lastTradedPrice": 9.35,
    "securityName": "Siddhartha Investment Growth Scheme - 2",
    "symbol": "SIGS2"
  },
  {
    "securityId": 634,
    "totalTrades": 5,
    "lastTradedPrice": 12089.2,
    "securityName": "Rastriya Beema Company Limited Promoter Share",
    "symbol": "RBCLPO"
  },
  {
    "securityId": 219,
    "totalTrades": 4,
    "lastTradedPrice": 47200.0,
    "securityName": "Unilever Nepal Limited",
    "symbol": "UNL"
  },
  {
    "securityId": 2879,
    "totalTrades": 4,
    "lastTradedPrice": 1149.0,
    "securityName": "10% Laxmi Bank Debenture 2086",
    "symbol": "LBLD86"
  },
  {
    "securityId": 9198,
    "totalTrades": 4,
    "lastTradedPrice": 9.0,
    "securityName": "Laxmi Value Fund 2",
    "symbol": "LVF2"
  },
  {
    "securityId": 2862,
    "totalTrades": 3,
    "lastTradedPrice": 9.11,
    "securityName": "CITIZENS MUTUAL FUND 2",
    "symbol": "CMF2"
  },
  {
    "securityId": 9249,
    "totalTrades": 3,
    "lastTradedPrice": 1130.0,
    "securityName": "9% ICFC Finance Limited Debenture 2088",
    "symbol": "ICFCD88"
  },
  {
    "securityId": 9241,
    "totalTrades": 3,
    "lastTradedPrice": 8.8,
    "securityName": "Kumari Sabal Yojana",
    "symbol": "KSY"
  },
  {
    "securityId": 8043,
    "totalTrades": 3,
    "lastTradedPrice": 1239.3,
    "securityName": "Civil Bank Debenture 2088",
    "symbol": "CBLD88"
  },
  {
    "securityId": 8110,
    "totalTrades": 3,
    "lastTradedPrice": 1091.3,
    "securityName": "10.25% Nepal SBI Bank Debenture 2083",
    "symbol": "SBID83"
  },
  {
    "securityId": 9289,
    "totalTrades": 3,
    "lastTradedPrice": 1070.0,
    "securityName": "7% Nepal SBI Bank Debenture 2090",
    "symbol": "SBID2090"
  },
  {
    "securityId": 9161,
    "totalTrades": 2,
    "lastTradedPrice": 6287.9,
    "securityName": "Aatmanirbhar Laghubitta Bittiya Sanstha Limited",
    "symbol": "ANLB"
  },
  {
    "securityId": 8119,
    "totalTrades": 2,
    "lastTradedPrice": 1173.0,
    "securityName": "10.50% Everest Bank Limited Debenture 2085",
    "symbol": "EBLD85"
  },
  {
    "securityId": 544,
    "totalTrades": 2,
    "lastTradedPrice": 100.0,
    "securityName": "Prime Commercial Bank Promoter Share",
    "symbol": "PCBLP"
  },
  {
    "securityId": 2932,
    "totalTrades": 2,
    "lastTradedPrice": 1154.7,
    "securityName": "9.5% Manjushree Finance Limited Debenture 2085",
    "symbol": "MFLD85"
  },
  {
    "securityId": 9271,
    "totalTrades": 2,
    "lastTradedPrice": 1081.0,
    "securityName": "7.25% SBL Debenture 2091",
    "symbol": "SBLD2091"
  },
  {
    "securityId": 2863,
    "totalTrades": 2,
    "lastTradedPrice": 8.72,
    "securityName": "NIC Asia Balanced Fund",
    "symbol": "NICBF"
  },
  {
    "securityId": 9211,
    "totalTrades": 1,
    "lastTradedPrice": 1158.0,
    "securityName": "9% Nepal SBI Bank Rinpatra 2089",
    "symbol": "SBID89"
  },
  {
    "securityId": 2866,
    "totalTrades": 1,
    "lastTradedPrice": 1176.1,
    "securityName": "10.25% Machhapuchhre Bank Debenture 2085",
    "symbol": "MBLD2085"
  },
  {
    "securityId": 2867,
    "totalTrades": 1,
    "lastTradedPrice": 10.3,
    "securityName": "NMB 50",
    "symbol": "NMB50"
  },
  {
    "securityId": 2747,
    "totalTrades": 1,
    "lastTradedPrice": 675.0,
    "securityName": "National Laghubitta Bittiya Sanstha Limited Promoter",
    "symbol": "NMFBSP"
  },
  {
    "securityId": 2936,
    "totalTrades": 1,
    "lastTradedPrice": 1158.8,
    "securityName": "9.5% NCC Debenture 2086",
    "symbol": "NCCD86"
  },
  {
    "securityId": 283,
    "totalTrades": 1,
    "lastTradedPrice": 106.9,
    "securityName": "Kumari Bank Limited Promotor Share",
    "symbol": "KBLPO"
  },
  {
    "securityId": 4959,
    "totalTrades": 1,
    "lastTradedPrice": 1130.1,
    "securityName": "8.5% Nepal Bank Debenture 2087",
    "symbol": "NBLD87"
  },
  {
    "securityId": 4961,
    "totalTrades": 1,
    "lastTradedPrice": 1115.0,
    "securityName": "8.5% BOK Debenture 2086",
    "symbol": "BOKD86"
  },
  {
    "securityId": 8033,
    "totalTrades": 1,
    "lastTradedPrice": 1095.0,
    "securityName": "Garima Debenture, 2085",
    "symbol": "GBBD85"
  },
  {
    "securityId": 2931,
    "totalTrades": 1,
    "lastTradedPrice": 1130.0,
    "securityName": "8.5% Nepal Investment Bank Debenture 2084",
    "symbol": "NIBD84"
  },
  {
    "securityId": 9141,
    "totalTrades": 1,
    "lastTradedPrice": 1080.0,
    "securityName": "NIFRA Uraj Rinpatra7%-2085/86",
    "symbol": "NIFRAUR85/86"
  },
  {
    "securityId": 9264,
    "totalTrades": 1,
    "lastTradedPrice": 1080.0,
    "securityName": "7% RBBL Debenture 2088",
    "symbol": "RBBD2088"
  },
  {
    "securityId": 9299,
    "totalTrades": 1,
    "lastTradedPrice": 1076.6,
    "securityName": "7% Nabil Debenture 2089",
    "symbol": "NABILD2089"
  }
]