[
  {
    "id": 57,
    "auditId": null,
    "exchangeIndexId": null,
    "generatedTime": "2025-11-23T15:18:30.653",
    "index": "Sensitive Index",
    "close": 440.65,
    "high": 448.2919,
    "low": 441.1861,
    "previousClose": 448.2919,
    "change": 7.63,
    "perChange": 1.73,
    "fiftyTwoWeekHigh": 518.6,
    "fiftyTwoWeekLow": 434.98,
    "currentValue": 448.29
  },
  {
    "id": 58,
    "auditId": null,
    "exchangeIndexId": null,
    "generatedTime": "2025-11-23T15:18:30.653",
    "index": "NEPSE Index",
    "close": 2560.29,
    "high": 2600.935,
    "low": 2562.3434,
    "previousClose": 2600.2214,
    "change": 39.92,
    "perChange": 1.55,
    "fiftyTwoWeekHigh": 3002.08,
    "fiftyTwoWeekLow": 2487.18,
    "currentValue": 2600.22
  },
  {
    "id": 62,
    "auditId": null,
    "exchangeIndexId": null,
    "generatedTime": "2025-11-23T15:18:30.657",
    "index": "Float Index",
    "close": 174.8,
    "high": 177.8552,
    "low": 174.9529,
    "previousClose": 177.8552,
    "change": 3.05,
    "perChange": 1.74,
    "fiftyTwoWeekHigh": 206.26,
    "fiftyTwoWeekLow": 170.58,
    "currentValue": 177.85
  },
  {
    "id": 63,
    "auditId": null,
    "exchangeIndexId": null,
    "generatedTime": "2025-11-23T15:18:30.657",
    "index": "Sensitive Float Index",
    "close": 149.37,
    "high": 152.0361,
    "low": 149.5725,
    "previousClose": 152.0361,
    "change": 2.66,
    "perChange": 1.78,
    "fiftyTwoWeekHigh": 177.31,
    "fiftyTwoWeekLow": 145.59,
    "currentValue": 152.03
  }
]