[
  {
    "id": 57,
    "auditId": null,
    "exchangeIndexId": null,
    "generatedTime": null,
    "index": "Sensitive Index",
    "close": 455.66,
    "high": 455.8372,
    "low": 451.8438,
    "previousClose": 452.6715,
    "change": -2.99,
    "perChange": -0.65,
    "fiftyTwoWeekHigh": 518.6,
    "fiftyTwoWeekLow": 434.98,
    "currentValue": 452.67
  },
  {
    "id": 58,
    "auditId": null,
    "exchangeIndexId": null,
    "generatedTime": null,
    "index": "NEPSE Index",
    "close": 2662.91,
    "high": 2665.8213,
    "low": 2636.4097,
    "previousClose": 2642.1503,
    "change": -20.75,
    "perChange": -0.77,
    "fiftyTwoWeekHigh": 3002.08,
    "fiftyTwoWeekLow": 2487.18,
    "currentValue": 2642.15
  },
  {
    "id": 62,
    "auditId": null,
    "exchangeIndexId": null,
    "generatedTime": null,
    "index": "Float Index",
    "close": 183.27,
    "high": 183.4214,
    "low": 181.2005,
    "previousClose": 181.6765,
    "change": -1.59,
    "perChange": -0.86,
    "fiftyTwoWeekHigh": 206.26,
    "fiftyTwoWeekLow": 170.58,
    "currentValue": 181.67
  },
  {
    "id": 63,
    "auditId": null,
    "exchangeIndexId": null,
    "generatedTime": null,
    "index": "Sensitive Float Index",
    "close": 155.49,
    "high": 155.5779,
    "low": 154.06,
    "previousClose": 154.4084,
    "change": -1.08,
    "perChange": -0.69,
    "fiftyTwoWeekHigh": 177.31,
    "fiftyTwoWeekLow": 145.59,
    "currentValue": 154.4
  }
]